geekbot_mcp/__init__.py
geekbot_mcp/gb_api.py
geekbot_mcp/models.py
geekbot_mcp/server.py
geekbot_mcp/settings.py
geekbot_mcp/prompts/__init__.py
geekbot_mcp/prompts/weekly_rollup_report.py
geekbot_mcp/tools/__init__.py
geekbot_mcp/tools/fetch_poll_results.py
geekbot_mcp/tools/fetch_reports.py
geekbot_mcp/tools/list_members.py
geekbot_mcp/tools/list_polls.py
geekbot_mcp/tools/list_standups.py
geekbot_mcp/tools/post_report.py
mseep_geekbot_mcp-0.3.8.dist-info/licenses/LICENSE
mseep_geekbot_mcp-0.3.8.dist-info/METADATA
mseep_geekbot_mcp-0.3.8.dist-info/WHEEL
mseep_geekbot_mcp-0.3.8.dist-info/entry_points.txt
mseep_geekbot_mcp-0.3.8.dist-info/top_level.txt
mseep_geekbot_mcp-0.3.8.dist-info/RECORD
