Metadata-Version: 2.4
Name: mseep-geekbot-mcp
Version: 0.3.8
Summary: Model Context Protocol (MCP) server integrating Geekbot data and tools to Claude AI
Author-email: mseep <support@skydeck.ai>
License: MIT
Project-URL: Homepage, https://github.com/geekbot-com/geekbot-mcp
Project-URL: Bug Tracker, https://github.com/geekbot-com/geekbot-mcp/issues
Keywords: geekbot,claude,ai,llm,mcp,api,integration,chatbot,anthropic
Classifier: Programming Language :: Python :: 3
Classifier: License :: OSI Approved :: MIT License
Classifier: Operating System :: OS Independent
Classifier: Programming Language :: Python :: 3
Classifier: Programming Language :: Python :: 3.10
Classifier: Programming Language :: Python :: 3.11
Classifier: Programming Language :: Python :: 3.12
Classifier: Topic :: Communications :: Chat
Classifier: Topic :: Scientific/Engineering :: Artificial Intelligence
Classifier: Topic :: Software Development :: Libraries :: Python Modules
Classifier: Topic :: Internet
Requires-Python: >=3.10
License-File: LICENSE
Requires-Dist: aiohttp>=3.11.14
Requires-Dist: jinja2>=3.1.6
Requires-Dist: mcp[cli]>=1.5.0
Requires-Dist: python-dotenv>=1.1.0
Dynamic: license-file
